{
  "anuvakam": 1,
  "title": "प्रथमोनुवाकः",
  "id": 2,
  "samhita": "या त॒ इषुः॑ शि॒वत॑मा शि॒व-म्ब॒भूव॑ ते॒ धनुः॑ । शि॒वा श॑र॒व्या॑ या तव॒ तया॑ नो रुद्र मृडय ॥",
  "pada": "या । ते॒ । इषुः॑ । शि॒व॒-तमा॑ । शि॒वम् । ब॒भूव॑ । ते॒ । धनुः॑ । शि॒वा । श॒र॒व्या॑ । या । तव॑ । तया॑ । नः॒ । रु॒द्र॒ । मृ॒ड॒य॒ ॥",
  "krama": "या ते॒ । ते इषुः॑ । इषुः॑ शि॒वत॑मा । शि॒वत॑मा शि॒वम् । शि॒व-म्ब॒भूव॑ । ब॒भूव॑ ते॒ । ते धनुः॑ । धनु॒रिति॑ धनुः॑ । शि॒वा श॑र॒व्या॑ । श॒र॒व्या॑ या । या तव॑ । तव॒ तया॑ । तया॑ नः । नः॒ रु॒द्र॒ । रु॒द्र मृ॒डय । मृ॒ड॒येति॑ मृडय ॥",
  "commentaries": {
    "sayana": {
      "rishi": "Kashyapa",
      "chandas": "Anushtup",
      "devata": "Rudra",
      "text": "O Rudra, that arrow of yours which has become most auspicious (shivatama), most peaceful. Similarly, that bow of yours which has become auspicious (shivam), peaceful. And that quiver (sharavya) of yours which is auspicious—with that peaceful arrow, that peaceful bow, and that peaceful quiver, make us (nah) happy (mridaya), give us joy. Their 'peacefulness' consists in the absence of their application against devotees. (2)\n...",
      "sanskrit": "हे रुद्र ते त्वदीया येयमिषुः शिवतमा शान्ततमा बभूव । तथा ते\nत्वदीयं यद्धनुः शिवं शान्तं बभूव । तथा या च तंव शरव्या तवेषुघिस्तया\nशान्तयेष्वा तेन च शान्तेन धनुषा तया च शान्तया शरव्यया नोऽस्मा-\nन्मृडय सुखय । भक्तेषु प्रवृत्यभावाचेषां शान्तत्वम् ॥ २ ॥\n\n\nभ०भा०भा० या त इषुः शिवतमेत्यस्याऽऽत्रेय ऋषिः । शंभुर्देवता । अनुष्टु-\nप्छन्दः । हे रुद्र या ते तवेपुः शिवतमाऽतिशयेन भक्तानां सुखकरी ।\nन केवलं हस्तालंकारमात्रभूता वभूवेति वक्ष्यमाणमनुपज्यते भवतीत्यर्थः ।\n\"छन्दासि लुहृलङ्कृलितः\" इति वतैमाने लिट् । शिवं वभूव ते धनुः । तत्रापि\nयच्छब्दोऽध्याहार्यः । यच्च ते धनुः शिवं वभूव ते भक्तान्मति सुखकरं भवति\nन केवलं हस्तान्तरमखंकरोति । या च तव शरव्या शिवा भक्तानां सुखकरी\nच । गृणातेर्हिंसाकर्मण उभत्यये शरुशब्देनाऽऽयुधमुच्यते । \" धुनिः शिमीवा-\nञ्छर्माञ्च ऋजीषी \" इति हि इरुयते । ततः समूहे स्वार्थे वा यमत्ययस्तदन्तं\nच क्षेपणीये चक्रादौ वर्तते । इरुयते हि \"अवष्टष्ठा परापत शरव्ये ब्रह्म-\nसखिता \" इति । संज्ञाशब्दत्पाञ्चीलिङ्गता । यद्वा पाशादिलक्षणो यमत्ययः ।\nछान्दसमन्तस्वरितत्वम् । यद्वा शरवः शरास्तेभ्यो हिता शरव्या इषुधिः ।\nपूर्वंवत्स्त्रीलिङ्गता । सर्वासामिषूणां शिवत्वाचदाधारस्य शिवत्वमार्थेना । यथा\nग्रामः मसीदित्विति । यद्वा मा भूविष्णूनामपादानमित्याशास्ते । यथा वक्ष्यते-\n\" अथो य इषुधिस्तवारे असि्मन्निपेहि तम् \" । इति । तया नोऽस्मान्मृडय\nसुखय । कयाऽनन्तरमकृतया शरव्यया उपलक्षणत्वाच्चेष्वा तया तेन च\nधनुषा । यद्वा लिङ्गसंख्ये अविवक्षिते । व्यत्ययो वा द्वयोः । तैरिष्वादि-\nभिरस्मान्मृडयेत्यर्थः । यद्वा करणविभक्तेः ' सुपां सुलुकू ' इति यादेशः ।\nएवमीदृशीं शान्तां तनुं गृहीत्वाऽस्मान्मृडयेत्याशास्ते घोरतनूपसंहाराथंम्\n' संज्ञापूर्वंको विधिरनित्यः ' इति मृडेलेंघ्रूपधगुणो न क्रियते । ' तवममौ\nछन्दसि ' इति तवशब्द् आश्युदात्तः । एतन्मश्रं द्वादशदिनानि चरुभोजीः\nजपित्वा कृतपुरश्चरणो विनियोकुं योग्यो भवति । अत्रार्थी ततस्तिलतण्डु-\nलयावकामलकल्कमेकादशसहस्सं जुहुयादन्वगनभिजायते । एतेन राजा दुभि-\nक्षनिवारणार्थे तिलगुडमिश्रितचरुणा स्वाम्रौ शतसहस्समाहुतीः कारयेत् ।\nततः सुभिक्षमभिजायते राज्ये । ध्यानम्—\n\" ध्यायेदेवं सुस्मितं स्यन्दनस्थं देव्या साथें तेजसा दीप्यमानम् ।\nइष्टिवषासालंकृताभ्यां कराभ्यां शूराकारं स्तूयमानं सुरायैः \" ॥२॥\n॥ तृतीयास्तृचमाह ॥\n\nया ते रुद्र शिवा तनूरघोराऽपापकाशिनी ।\nतया नस्तनुवा शंतमया गिरिशंताभिचाकशीहि ॥ ३ ॥\nया ते रुद्र शिवा तनुः अघोरा अपापकाशिनीत्यपाप-"
    },
    "bhatta_bhaskara": {
      "rishi": "Kashyapa",
      "chandas": "Anushtup",
      "devata": "Rudra",
      "dhyana": "Meditation on Shiva as detailed in standard commentaries.",
      "text": "",
      "sanskrit": ""
    },
    "abhinava_shankara": {
      "rishi": "Atreya",
      "chandas": "Anushtup",
      "devata": "Sri Rudra",
      "dhyana": "Meditation on Lord Maheshvara with resplendent Goddess.",
      "text": "",
      "sanskrit": ""
    }
  },
  "samhita_tokens": [
    {
      "text": "या",
      "word_ids": [
        44
      ]
    },
    {
      "text": " ",
      "word_ids": []
    },
    {
      "text": "त॒",
      "word_ids": [
        2
      ]
    },
    {
      "text": " ",
      "word_ids": []
    },
    {
      "text": "इषुः॑",
      "word_ids": [
        66
      ]
    },
    {
      "text": " ",
      "word_ids": []
    },
    {
      "text": "शि॒वत॑मा",
      "word_ids": [
        67
      ]
    },
    {
      "text": " ",
      "word_ids": []
    },
    {
      "text": "शि॒व-म्ब॒भूव॑",
      "word_ids": [
        68,
        47
      ]
    },
    {
      "text": " ",
      "word_ids": []
    },
    {
      "text": "ते॒",
      "word_ids": [
        2
      ]
    },
    {
      "text": " ",
      "word_ids": []
    },
    {
      "text": "धनुः॑",
      "word_ids": [
        26
      ]
    },
    {
      "text": " । ",
      "word_ids": []
    },
    {
      "text": "शि॒वा",
      "word_ids": [
        69
      ]
    },
    {
      "text": " ",
      "word_ids": []
    },
    {
      "text": "श॑र॒व्या॑",
      "word_ids": [
        70,
        44
      ]
    },
    {
      "text": " ",
      "word_ids": []
    },
    {
      "text": "या",
      "word_ids": []
    },
    {
      "text": " ",
      "word_ids": []
    },
    {
      "text": "तव॒",
      "word_ids": [
        57
      ]
    },
    {
      "text": " ",
      "word_ids": []
    },
    {
      "text": "तया॑",
      "word_ids": [
        48
      ]
    },
    {
      "text": " ",
      "word_ids": []
    },
    {
      "text": "नो",
      "word_ids": [
        33
      ]
    },
    {
      "text": " ",
      "word_ids": []
    },
    {
      "text": "रुद्र",
      "word_ids": [
        3
      ]
    },
    {
      "text": " ",
      "word_ids": []
    },
    {
      "text": "मृडय",
      "word_ids": [
        71
      ]
    },
    {
      "text": " ॥",
      "word_ids": []
    }
  ],
  "pada_tokens": [
    {
      "text": "या",
      "word_ids": [
        44
      ]
    },
    {
      "text": " । ",
      "word_ids": []
    },
    {
      "text": "ते॒",
      "word_ids": [
        2
      ]
    },
    {
      "text": " । ",
      "word_ids": []
    },
    {
      "text": "इषुः॑",
      "word_ids": [
        66
      ]
    },
    {
      "text": " । ",
      "word_ids": []
    },
    {
      "text": "शि॒व॒-तमा॑",
      "word_ids": [
        67
      ]
    },
    {
      "text": " । ",
      "word_ids": []
    },
    {
      "text": "शि॒वम्",
      "word_ids": [
        68
      ]
    },
    {
      "text": " । ",
      "word_ids": []
    },
    {
      "text": "ब॒भूव॑",
      "word_ids": [
        47
      ]
    },
    {
      "text": " । ",
      "word_ids": []
    },
    {
      "text": "ते॒",
      "word_ids": [
        2
      ]
    },
    {
      "text": " । ",
      "word_ids": []
    },
    {
      "text": "धनुः॑",
      "word_ids": [
        26
      ]
    },
    {
      "text": " । ",
      "word_ids": []
    },
    {
      "text": "शि॒वा",
      "word_ids": [
        69
      ]
    },
    {
      "text": " । ",
      "word_ids": []
    },
    {
      "text": "श॒र॒व्या॑",
      "word_ids": [
        70,
        44
      ]
    },
    {
      "text": " । ",
      "word_ids": []
    },
    {
      "text": "या",
      "word_ids": []
    },
    {
      "text": " । ",
      "word_ids": []
    },
    {
      "text": "तव॑",
      "word_ids": [
        57
      ]
    },
    {
      "text": " । ",
      "word_ids": []
    },
    {
      "text": "तया॑",
      "word_ids": [
        48
      ]
    },
    {
      "text": " । ",
      "word_ids": []
    },
    {
      "text": "नः॒",
      "word_ids": [
        33
      ]
    },
    {
      "text": " । ",
      "word_ids": []
    },
    {
      "text": "रु॒द्र॒",
      "word_ids": [
        3
      ]
    },
    {
      "text": " । ",
      "word_ids": []
    },
    {
      "text": "मृ॒ड॒य॒",
      "word_ids": [
        71
      ]
    },
    {
      "text": " ॥",
      "word_ids": []
    }
  ],
  "krama_tokens": [
    {
      "text": "या",
      "word_ids": [
        44
      ]
    },
    {
      "text": " ",
      "word_ids": []
    },
    {
      "text": "ते॒",
      "word_ids": [
        2
      ]
    },
    {
      "text": " । ",
      "word_ids": []
    },
    {
      "text": "ते",
      "word_ids": [
        2
      ]
    },
    {
      "text": " ",
      "word_ids": []
    },
    {
      "text": "इषुः॑",
      "word_ids": [
        66
      ]
    },
    {
      "text": " । ",
      "word_ids": []
    },
    {
      "text": "इषुः॑",
      "word_ids": [
        66
      ]
    },
    {
      "text": " ",
      "word_ids": []
    },
    {
      "text": "शि॒वत॑मा",
      "word_ids": [
        2
      ]
    },
    {
      "text": " । ",
      "word_ids": []
    },
    {
      "text": "शि॒वत॑मा",
      "word_ids": [
        2
      ]
    },
    {
      "text": " ",
      "word_ids": []
    },
    {
      "text": "शि॒वम्",
      "word_ids": [
        67
      ]
    },
    {
      "text": " । ",
      "word_ids": []
    },
    {
      "text": "शि॒व-म्ब॒भूव॑",
      "word_ids": [
        67,
        47
      ]
    },
    {
      "text": " । ",
      "word_ids": []
    },
    {
      "text": "ब॒भूव॑",
      "word_ids": [
        47
      ]
    },
    {
      "text": " ",
      "word_ids": []
    },
    {
      "text": "ते॒",
      "word_ids": [
        2
      ]
    },
    {
      "text": " । ",
      "word_ids": []
    },
    {
      "text": "ते",
      "word_ids": [
        2
      ]
    },
    {
      "text": " ",
      "word_ids": []
    },
    {
      "text": "धनुः॑",
      "word_ids": [
        26
      ]
    },
    {
      "text": " । ",
      "word_ids": []
    },
    {
      "text": "धनु॒रिति॑",
      "word_ids": [
        2
      ]
    },
    {
      "text": " ",
      "word_ids": []
    },
    {
      "text": "धनुः॑",
      "word_ids": [
        26
      ]
    },
    {
      "text": " । ",
      "word_ids": []
    },
    {
      "text": "शि॒वा",
      "word_ids": [
        69
      ]
    },
    {
      "text": " ",
      "word_ids": []
    },
    {
      "text": "श॑र॒व्या॑",
      "word_ids": [
        69,
        44
      ]
    },
    {
      "text": " । ",
      "word_ids": []
    },
    {
      "text": "श॒र॒व्या॑",
      "word_ids": [
        70,
        44
      ]
    },
    {
      "text": " ",
      "word_ids": []
    },
    {
      "text": "या",
      "word_ids": [
        44
      ]
    },
    {
      "text": " । ",
      "word_ids": []
    },
    {
      "text": "या",
      "word_ids": [
        44
      ]
    },
    {
      "text": " ",
      "word_ids": []
    },
    {
      "text": "तव॑",
      "word_ids": [
        57
      ]
    },
    {
      "text": " । ",
      "word_ids": []
    },
    {
      "text": "तव॒",
      "word_ids": [
        57
      ]
    },
    {
      "text": " ",
      "word_ids": []
    },
    {
      "text": "तया॑",
      "word_ids": [
        44
      ]
    },
    {
      "text": " । ",
      "word_ids": []
    },
    {
      "text": "तया॑",
      "word_ids": [
        44
      ]
    },
    {
      "text": " ",
      "word_ids": []
    },
    {
      "text": "नः",
      "word_ids": [
        33
      ]
    },
    {
      "text": " । ",
      "word_ids": []
    },
    {
      "text": "नः॒",
      "word_ids": [
        33
      ]
    },
    {
      "text": " ",
      "word_ids": []
    },
    {
      "text": "रु॒द्र॒",
      "word_ids": [
        3
      ]
    },
    {
      "text": " । ",
      "word_ids": []
    },
    {
      "text": "रु॒द्र",
      "word_ids": [
        3
      ]
    },
    {
      "text": " ",
      "word_ids": []
    },
    {
      "text": "मृ॒डय",
      "word_ids": [
        71
      ]
    },
    {
      "text": " । ",
      "word_ids": []
    },
    {
      "text": "मृ॒ड॒येति॑",
      "word_ids": [
        71
      ]
    },
    {
      "text": " ",
      "word_ids": []
    },
    {
      "text": "मृडय",
      "word_ids": [
        71
      ]
    },
    {
      "text": " ॥",
      "word_ids": []
    }
  ],
  "words": [
    2,
    3,
    26,
    33,
    44,
    47,
    48,
    57,
    66,
    67,
    68,
    69,
    70,
    71
  ]
}